[
  {
    "league": "\ud83c\udfc6T20 World Cup",
    "match_link": "https://www.yonotvs.com/p/match-details.html?id=eng",
    "home_team": "England",
    "home_flag": "https://aimages.willow.tv/teamLogos/england.png",
    "away_team": "Sri Lanka",
    "away_flag": "https://aimages.willow.tv/teamLogos/srilanka.png",
    "start_time": "2026-02-22T15:15:00+05:45",
    "end_time": "2026-02-22T19:00:00+05:45"
  },
  {
    "league": "\ud83c\udfc6T20 World Cup",
    "match_link": "https://www.yonotvs.com/p/match-details.html?id=india",
    "home_team": "India",
    "home_flag": "https://aimages.willow.tv/teamLogos/india.png",
    "away_team": "South Africa",
    "away_flag": "https://aimages.willow.tv/teamLogos/southafrica.png",
    "start_time": "2026-02-22T19:15:00+05:45",
    "end_time": "2026-02-22T23:30:00+05:45"
  },
  {
    "league": "\ud83c\udfc6MLS",
    "match_link": "https://www.yonotvs.com/p/match-details.html?id=inter",
    "home_team": "Inter Miami",
    "home_flag": "https://images.fotmob.com/image_resources/logo/teamlogo/960720.png",
    "away_team": "Los Angeles",
    "away_flag": "https://images.fotmob.com/image_resources/logo/teamlogo/867280.png",
    "start_time": "2026-02-22T08:15:00+05:45",
    "end_time": "2026-02-22T10:15:00+05:45"
  },
  {
    "league": "\ud83c\udfc6Premier League",
    "match_link": "https://www.yonotvs.com/p/match-details.html?id=liverpool",
    "home_team": "Liverpool",
    "home_flag": "https://images.fotmob.com/image_resources/logo/teamlogo/8650.png",
    "away_team": "Nottingham",
    "away_flag": "https://images.fotmob.com/image_resources/logo/teamlogo/10203.png",
    "start_time": "2026-02-22T19:45:00+05:45",
    "end_time": "2026-02-22T22:00:00+05:45"
  },
  {
    "league": "\ud83c\udfc6Premier League",
    "match_link": "https://www.yonotvs.com/p/match-details.html?id=arsenal",
    "home_team": "Tottenham",
    "home_flag": "https://images.fotmob.com/image_resources/logo/teamlogo/8586.png",
    "away_team": "Arsenal",
    "away_flag": "https://images.fotmob.com/image_resources/logo/teamlogo/9825.png",
    "start_time": "2026-02-22T22:15:00+05:45",
    "end_time": "2026-02-23T00:15:00+05:45"
  },
  {
    "league": "\ud83c\udfc6La Liga",
    "match_link": "https://www.yonotvs.com/p/match-details.html?id=barcelona",
    "home_team": "Barcelona",
    "home_flag": "https://images.fotmob.com/image_resources/logo/teamlogo/8634.png",
    "away_team": "Levante",
    "away_flag": "https://storage.livescore.com/images/team/high/enet/8581.png",
    "start_time": "2026-02-22T21:00:00+05:45",
    "end_time": "2026-02-22T11:15:00+05:45"
  }
]